pymetrics/__init__.py
pymetrics/configuration.py
pymetrics/instruments.py
pymetrics/py.typed
pymetrics/version.py
pymetrics/publishers/__init__.py
pymetrics/publishers/base.py
pymetrics/publishers/datadog.py
pymetrics/publishers/logging.py
pymetrics/publishers/null.py
pymetrics/publishers/sql.py
pymetrics/publishers/sqlite.py
pymetrics/publishers/statsd.py
pymetrics/publishers/utils.py
pymetrics/recorders/__init__.py
pymetrics/recorders/base.py
pymetrics/recorders/default.py
pymetrics/recorders/noop.py
pymetrics-1.0.10.dist-info/LICENSE
pymetrics-1.0.10.dist-info/METADATA
pymetrics-1.0.10.dist-info/WHEEL
pymetrics-1.0.10.dist-info/top_level.txt
pymetrics-1.0.10.dist-info/RECORD
