Metadata-Version: 2.1
Name: pymetrics
Version: 1.0.10
Summary: Versatile metrics collection for Python
Home-page: https://github.com/eventbrite/pymetrics
Author: Eventbrite, Inc.
Author-email: opensource@eventbrite.com
License: Apache 2.0
Project-URL: Documentation, https://pymetrics.readthedocs.io
Project-URL: Issues, https://github.com/eventbrite/pymetrics/issues
Project-URL: CI, https://travis-ci.org/eventbrite/pymetrics/
Classifier: Development Status :: 5 - Production/Stable
Classifier: Intended Audience :: Developers
Classifier: License :: OSI Approved :: Apache Software License
Classifier: Operating System :: OS Independent
Classifier: Programming Language :: Python
Classifier: Programming Language :: Python :: 2
Classifier: Programming Language :: Python :: 2.7
Classifier: Programming Language :: Python :: 3
Classifier: Programming Language :: Python :: 3.5
Classifier: Programming Language :: Python :: 3.6
Classifier: Programming Language :: Python :: 3.7
Classifier: Programming Language :: Python :: 3.8
Classifier: Topic :: Software Development
Provides-Extra: testing
Provides-Extra: docs
License-File: LICENSE
